{
  "accentColor": "{{appsmith.theme.colors.primaryColor}}",
  "animateLoading": true,
  "borderRadius": "{{appsmith.theme.borderRadius.appBorderRadius}}",
  "bottomRow": 33,
  "boxShadow": "none",
  "closeOnSelection": true,
  "dateFormat": "DD/MM/YYYY",
  "datePickerType": "DATE_PICKER",
  "dynamicBindingPathList": [
    {
      "key": "accentColor"
    },
    {
      "key": "borderRadius"
    }
  ],
  "dynamicHeight": "FIXED",
  "dynamicTriggerPathList": [
    {
      "key": "onFocus"
    }
  ],
  "firstDayOfWeek": 0,
  "isDisabled": false,
  "isLoading": false,
  "isRequired": false,
  "isVisible": true,
  "key": "v15am5gdlg",
  "label": "Date d'écheance",
  "labelAlignment": "left",
  "labelPosition": "Top",
  "labelTextSize": "0.875rem",
  "labelWidth": 5,
  "leftColumn": 2,
  "maxDate": "2121-12-31T18:29:00.000Z",
  "maxDynamicHeight": 9000,
  "minDate": "1920-12-31T18:30:00.000Z",
  "minDynamicHeight": 4,
  "minWidth": 450,
  "mobileBottomRow": 36,
  "mobileLeftColumn": 3,
  "mobileRightColumn": 23,
  "mobileTopRow": 29,
  "needsErrorInfo": false,
  "onFocus": "",
  "parentColumnSpace": 6.9375,
  "parentId": "hxw6kcav35",
  "parentRowSpace": 10,
  "renderMode": "CANVAS",
  "responsiveBehavior": "fill",
  "rightColumn": 38,
  "shortcuts": false,
  "timePrecision": "None",
  "topRow": 26,
  "type": "DATE_PICKER_WIDGET2",
  "version": 2,
  "widgetId": "hix7l7rb54",
  "widgetName": "Input_duedate"
}